LeanIX/FactSheets.py
LeanIX/Graph.py
LeanIX/Users.py
LeanIX/__init__.py
leanix_py-0.0.5.dist-info/LICENSE
leanix_py-0.0.5.dist-info/METADATA
leanix_py-0.0.5.dist-info/WHEEL
leanix_py-0.0.5.dist-info/top_level.txt
leanix_py-0.0.5.dist-info/RECORD
