Metadata-Version: 2.1
Name: leanix-py
Version: 0.0.5
Summary: Functionality to support the development with LeanIX REST APIs
Home-page: https://github.com/JeffGebhart/leanix-python-library
Author: Jeff Gebhart
Author-email: jeff@gebhart.ca
License: UNKNOWN
Platform: UNKNOWN
Classifier: Development Status :: 1 - Planning
Classifier: Intended Audience :: Developers
Classifier: License :: OSI Approved :: MIT License
Classifier: Programming Language :: Python :: 3
Requires-Dist: requests
